{
  "legislative_session": "36",
  "identifier": "36-0064",
  "title": "An Act amending title 33 Virgin Islands Code, chapter 111, section 3100i aligning the disbursement and spending limitations of funds allotted to public schools from the Education Initiative Fund with the realities of academic planning, ensuring that funds are used to maximize student success",
  "from_organization": "~{\"classification\": \"legislature\"}",
  "classification": [
    "bill"
  ],
  "subject": [],
  "abstracts": [],
  "other_titles": [],
  "other_identifiers": [],
  "actions": [
    {
      "description": "received",
      "date": "2025-02-18",
      "organization_id": "~{\"classification\": \"legislature\"}",
      "classification": [],
      "related_entities": [],
      "_processing": {
        "log_file_created": "2025-10-25T02:57:22Z"
      }
    },
    {
      "description": "Assigned",
      "date": "2025-02-19",
      "organization_id": "~{\"classification\": \"legislature\"}",
      "classification": [],
      "related_entities": [],
      "_processing": {
        "log_file_created": "2025-10-25T02:57:22Z"
      }
    },
    {
      "description": "To Senate",
      "date": "2025-02-24",
      "organization_id": "~{\"classification\": \"legislature\"}",
      "classification": [],
      "related_entities": [],
      "_processing": {
        "log_file_created": "2025-10-25T02:57:22Z"
      }
    },
    {
      "description": "Introduced",
      "date": "2025-03-28",
      "organization_id": "~{\"classification\": \"legislature\"}",
      "classification": [
        "introduction"
      ],
      "related_entities": [],
      "_processing": {
        "log_file_created": "2025-10-25T02:57:22Z"
      }
    },
    {
      "description": "Sent to Lt. Governor",
      "date": "2025-07-17",
      "organization_id": "~{\"classification\": \"legislature\"}",
      "classification": [
        "executive-receipt"
      ],
      "related_entities": [],
      "_processing": {
        "log_file_created": "2025-10-25T02:57:22Z"
      }
    },
    {
      "description": "Sent to Governor",
      "date": "2025-07-01",
      "organization_id": "~{\"classification\": \"legislature\"}",
      "classification": [
        "executive-receipt"
      ],
      "related_entities": [],
      "_processing": {
        "log_file_created": "2025-10-25T02:57:22Z"
      }
    },
    {
      "description": "Vetoed",
      "date": "2025-07-09",
      "organization_id": "~{\"classification\": \"legislature\"}",
      "classification": [
        "executive-veto"
      ],
      "related_entities": [],
      "_processing": {
        "log_file_created": "2025-10-25T02:57:22Z"
      }
    },
    {
      "description": "Approved by Governor",
      "date": "2025-07-09",
      "organization_id": "~{\"classification\": \"legislature\"}",
      "classification": [
        "executive-signature"
      ],
      "related_entities": [],
      "_processing": {
        "log_file_created": "2025-10-25T02:57:22Z"
      }
    }
  ],
  "sponsorships": [
    {
      "name": "Kurt A. Vialet",
      "classification": "primary",
      "entity_type": "person",
      "primary": true,
      "person_id": "~{\"name\": \"Kurt A. Vialet\"}",
      "organization_id": null
    }
  ],
  "related_bills": [],
  "versions": [
    {
      "note": "Bill 36-0064",
      "links": [
        {
          "url": "https://billtracking.legvi.org:8082/preview/Bill%2F36-0064",
          "media_type": "application/pdf"
        }
      ],
      "date": "",
      "classification": ""
    },
    {
      "note": "Act 9005",
      "links": [
        {
          "url": "https://billtracking.legvi.org:8082/preview/Act%2F9005",
          "media_type": "application/pdf"
        }
      ],
      "date": "",
      "classification": ""
    }
  ],
  "documents": [],
  "citations": [],
  "sources": [
    {
      "url": "https://billtracking.legvi.org/",
      "note": ""
    }
  ],
  "extras": {},
  "jurisdiction": {
    "id": "ocd-jurisdiction/country:us/territory:vi/government",
    "name": "Virgin Islands",
    "classification": "state",
    "division_id": "ocd-division/country:us/territory:vi"
  },
  "_processing": {
    "logs_latest_update": "2025-10-25T02:57:22Z"
  }
}